pygramcore/__init__.py
pygramcore/constants.py
pygramcore/pygram.py
pygramcore/elements/__init__.py
pygramcore/elements/post.py
pygramcore/elements/user.py
pygramcore/exceptions/__init__.py
pygramcore/exceptions/auth.py
pygramcore/exceptions/format.py
pygramcore/exceptions/navigation.py
pygramcore/exceptions/post.py
pygramcore/exceptions/user.py
pygramcore/utils/__init__.py
pygramcore/utils/misc.py
pygramcore/utils/navigation.py
pygramcore-1.1.0.dist-info/LICENSE
pygramcore-1.1.0.dist-info/METADATA
pygramcore-1.1.0.dist-info/WHEEL
pygramcore-1.1.0.dist-info/top_level.txt
pygramcore-1.1.0.dist-info/RECORD
